txsh-0.2.1.dist-info/top_level.txt
txsh-0.2.1.dist-info/RECORD
txsh-0.2.1.dist-info/DESCRIPTION.rst
txsh-0.2.1.dist-info/METADATA
txsh-0.2.1.dist-info/metadata.json
txsh-0.2.1.dist-info/WHEEL
txsh/testsh.py
txsh/__init__.py
txsh/resolvers.py
txsh/test.py
txsh/protocols.py
txsh/core.py
tests/__init__.py
tests/test_core.py
tests/test_protocols.py
